lazy_importing/__init__.py
lazy_importing/lazy_import.py
LazyImporting-0.2.dist-info/METADATA
LazyImporting-0.2.dist-info/WHEEL
LazyImporting-0.2.dist-info/top_level.txt
LazyImporting-0.2.dist-info/RECORD
