Metadata-Version: 2.1
Name: LazyImporting
Version: 0.2
Summary: This is a library for lazily importing modules
Home-page: https://github.com/lazy-importing/lazyimporting
Download-URL: https://github.com/lazy-importing/lazyimporting
Author: Laz Impo
Author-email: lazyimport@gmail.com
License: MIT
Classifier: Development Status :: 3 - Alpha
Classifier: Intended Audience :: Developers
Classifier: License :: OSI Approved :: MIT License
Classifier: Topic :: Software Development :: Build Tools
Classifier: Programming Language :: Python :: 3
